{"type":"FeatureCollection","features":[{"type":"Feature","id":1,"geometry":{"type":"Point","coordinates":[-90.087307579999958,35.07355412000004]},"properties":{"OBJECTID":1,"point_of_interest":"Colossus 1","description":"Colossus began operations in Memphis, Tenn., in July 2024. Its primary purpose is to train xAI's chatbot, Grok.","type":"xAI data center","location":"3231 Riverport Rd, Memphis, TN 38109","lat":35.073554119999997,"lon":-90.087307580000001,"housenumber":3231,"street":"Riverport Road","postcode":38109,"city":"Memphis","county":"Shelby County","county_code":"SHE","state":"Tennessee","state_code":"TN","country":"United States","country_code":"us","attribution":"© OpenStreetMap contributors","attribution_license":"Open Database License","attribution_url":"https://www.openstreetmap.org/copyright"}},{"type":"Feature","id":2,"geometry":{"type":"Point","coordinates":[-90.034867369999972,34.997982900000068]},"properties":{"OBJECTID":2,"point_of_interest":"Colossus 2","description":"xAI began construcccting Colossus 2, its second data center in Memphis, in spring of 2025. The facility's primary purpose is to train xAI's chatbot, Grok.","type":"xAI data center","location":"5420 Tulane Rd, Memphis, TN 38109","lat":34.997982899999997,"lon":-90.034867370000001,"housenumber":5420,"street":"Tulane Road","postcode":38109,"city":"Memphis","county":"Shelby County","county_code":"SHE","state":"Tennessee","state_code":"TN","country":"United States","country_code":"us","attribution":"© OpenStreetMap contributors","attribution_license":"Open Database License","attribution_url":"https://www.openstreetmap.org/copyright"}},{"type":"Feature","id":3,"geometry":{"type":"Point","coordinates":[-90.043288959999984,34.984354760000031]},"properties":{"OBJECTID":3,"point_of_interest":"Former Duke Energy Plant","description":"Since last summer, xAI has used unpermitted gas turbines at this site to supply power to the Colossus 2 data center.","type":"xAI power plant","location":"2875 Stanton Rd S, Southaven, MS 38671","lat":34.984354760000002,"lon":-90.043288959999998,"housenumber":2875,"street":"Stanton Road South","postcode":38671,"city":"Southaven","county":"DeSoto County","county_code":null,"state":"Mississippi","state_code":"MS","country":"United States","country_code":"us","attribution":"© OpenStreetMap contributors","attribution_license":"Open Database License","attribution_url":"https://www.openstreetmap.org/copyright"}},{"type":"Feature","id":4,"geometry":{"type":"Point","coordinates":[-90.034357999999941,34.991888000000074]},"properties":{"OBJECTID":4,"point_of_interest":"MACROHARDRR","description":"The site of xAI's planned 810,000-square-foot data center in Southaven, Mississippi. The facility was first announced in December 2025.","type":"xAI data center","location":"2400 Stateline Rd W, Southaven, MS 38671","lat":34.991888000000003,"lon":-90.034357999999997,"housenumber":2400,"street":"Stateline Road West","postcode":38671,"city":"Southaven","county":"DeSoto County","county_code":null,"state":"Mississippi","state_code":"MS","country":"United States","country_code":"us","attribution":"© OpenStreetMap contributors","attribution_license":"Open Database License","attribution_url":"https://www.openstreetmap.org/copyright"}}]}